LICENCE.txt
MANIFEST.in
README.rst
setup.py
autobreadcrumbs/__init__.py
autobreadcrumbs/context_processors.py
autobreadcrumbs/discover.py
autobreadcrumbs/models.py
autobreadcrumbs/registry.py
autobreadcrumbs/resolver.py
autobreadcrumbs/settings.py
autobreadcrumbs.egg-info/PKG-INFO
autobreadcrumbs.egg-info/SOURCES.txt
autobreadcrumbs.egg-info/dependency_links.txt
autobreadcrumbs.egg-info/not-zip-safe
autobreadcrumbs.egg-info/requires.txt
autobreadcrumbs.egg-info/top_level.txt
autobreadcrumbs/templates/autobreadcrumbs_tag.html
autobreadcrumbs/templatetags/__init__.py
autobreadcrumbs/templatetags/autobreadcrumb.py