Metadata-Version: 1.1
Name: autobreadcrumbs
Version: 2.0.0
Summary: 
